multi/or2.v
module OR2(A,B,X);

input A,B;
output X;

assign X = A | B;

endmodule

multi/and2.v
module AND2(A,B,X);

input A,B;
output X;

assign X = A & B;

endmodule

multi/xor2.v
module XOR2(A,B,X);

   input A,B;
   output X;

   assign X = A ^ B;

endmodule // XOR2

multi/halfadder_module.v
/* HALFADD */
module HALFADD(a, b, X, Y);
//count is and -> Y

  input a, b;
  output X, Y;
    
    XOR2 aaa(a, b, X);
    AND2 bbb(a, b, Y);
    /*assign X = A ^ B; /* XOR2 */
    /*assign Y = A & B; /* AND2 */

endmodule

multi/all_adder.v
module ALL_ADDER(a,b,cin,s,cout);

    input a,b,cin;
    output s1,c1,c2,s,cout;
    HALFADD half1(a,b,s1,c1);
    HALFADD half2(cin,s1,s,c2);
    OR2 b3(c1,c2,cout);

endmodule

multi/add4.v
module ADD4(t,d);

  input [3:0]t;
  output [3:0]d;
  wire c = 1;
  wire [3:0] x;

    // kougi pdf page [3] figure
    // Ex
    // 0010 = 2
    // 0011 = 3
    // ----
    // 0010 = 2
    // 0100 = 4
    // ----
    // 0110 = 6
    //
    // b4 & b1 = 0

    // xor -> b
    XOR2 b3(0, c, x[3]); //3
    XOR2 b2(0, c, x[2]); //2
    XOR2 b1(t[1], c, x[1]); //1 //left figure 0 & 0 and throw gate
    XOR2 b0(t[0], c, x[0]); //0
    
    // a4 & a1 = 0
    ALL_ADDER bb0(0, x[0],1, d[0], count0); //0
    ALL_ADDER bb1(t[3], x[1], count0, d[1], count1); //1
    ALL_ADDER bb2(t[2], x[2], count1, d[2], count2); //2
    ALL_ADDER bb3(0, x[3], count2, d[3], count3); //3

endmodule

multi/gate.v
module GATE(a1, a0, b, out1, out0);

input a1, a0, b;
output out1, out0;
wire nc,t1,t2;

AND2 b1(a0, b, out0);
AND2 b0(a1, b, out1);

endmodule

multi/multi2_module.v
module MULTI2(a,b,s);

  input [1:0] a; 
  input [1:0] b;
  output [3:0] s;
  wire [3:0] t;
  
  GATE gt1(a[1],a[0],b[1],t[3], t[2]);
  GATE gt2(a[1],a[0],b[0],t[1], t[0]);
  
  ADD4 bbb(t,s);

endmodule

multi/multi2_excute.v
module MULTI2TEST;


  reg [1:0] a;
  reg [1:0] b;
  wire [3:0] s;
  integer i, j, k, m;
  //reg a1,a0,b1,b0;
  //wire d3,d2,d1,d0;

  MULTI2 bbb(a,b,s);
    initial begin
      $dumpfile("mulit2test.vcd");
      $dumpvars(0,MULTI2TEST);
      $monitor("%t: a1 = %b, a0 = %b,b1 = %b, b0 = %b, d3 = %b, d2 = %b, d1 = %b, d0 = %b", $time, a[1],a[0],b[1],b[0],s[3],s[2],s[1],s[0]);

       a[1]=0; a[0]=0; b[1]=0; b[0]=0;
      // a = 2'b00; b = 2'b00;
      // b[1] = 0; b[0] = 0;
      // for (i = 0; i < 2; i = i + 1)
      //   for (k = 0; k < 2; k = k + 1)
      //     for (m = 0; m < 2; m = m + 1) begin
      //       #10 b[0] = i; a[1] = k; a[0] = m;
      //     end
      for(i=0; i<2; i=i+1) 
        for(j=0; j<2; j=j+1)
          for(k=0; k<2; k=k+1)
            for(m=0; m<2; m=m+1) begin
              #10 b[0] = j; b[1] = i; a[0] = m; a[1] = k;
            end

      //   a[1]=0; a[0]=0; b[1]=0; b[0]=0;
      // #10 a[1]=0; a[0]=1; b[1]=0; b[0]=0;
      // #10 a[1]=1; a[0]=0; b[1]=0; b[0]=0;
      // #10 a[1]=1; a[0]=1; b[1]=0; b[0]=0;
      // #10 a[1]=0; a[0]=0; b[1]=0; b[0]=1;
      // #10 a[1]=0; a[0]=1; b[1]=0; b[0]=1;
      // #10 a[1]=1; a[0]=0; b[1]=0; b[0]=1;
      // #10 a[1]=1; a[0]=1; b[1]=0; b[0]=1;
      // #10 a[1]=0; a[0]=0; b[1]=1; b[0]=0;
      // #10 a[1]=0; a[0]=1; b[1]=1; b[0]=0;
      // #10 a[1]=1; a[0]=0; b[1]=1; b[0]=0;
      // #10 a[1]=1; a[0]=1; b[1]=1; b[0]=0;
      // #10 a[1]=0; a[0]=0; b[1]=1; b[0]=1;
      // #10 a[1]=0; a[0]=1; b[1]=1; b[0]=1;
      // #10 a[1]=1; a[0]=0; b[1]=1; b[0]=1;
      // #10 a[1]=1; a[0]=1; b[1]=1; b[0]=1;
      #10 $finish;
    end
endmodule

multi/mulit2test.vcd
$date
	Fri Aug 10 00:46:01 2018
$end
$version
	Icarus Verilog
$end
$timescale
	1s
$end
$scope module MULTI2TEST $end
$var wire 4 ! s [3:0] $end
$var reg 2 " a [1:0] $end
$var reg 2 # b [1:0] $end
$var integer 32 $ i [31:0] $end
$var integer 32 % j [31:0] $end
$var integer 32 & k [31:0] $end
$var integer 32 ' m [31:0] $end
$scope module bbb $end
$var wire 2 ( a [1:0] $end
$var wire 2 ) b [1:0] $end
$var wire 4 * s [3:0] $end
$var wire 4 + t [3:0] $end
$scope module gt1 $end
$var wire 1 , a0 $end
$var wire 1 - a1 $end
$var wire 1 . b $end
$var wire 1 / out0 $end
$var wire 1 0 out1 $end
$scope module b1 $end
$var wire 1 , A $end
$var wire 1 . B $end
$var wire 1 / X $end
$upscope $end
$scope module b0 $end
$var wire 1 - A $end
$var wire 1 . B $end
$var wire 1 0 X $end
$upscope $end
$upscope $end
$scope module gt2 $end
$var wire 1 1 a0 $end
$var wire 1 2 a1 $end
$var wire 1 3 b $end
$var wire 1 4 out0 $end
$var wire 1 5 out1 $end
$scope module b1 $end
$var wire 1 1 A $end
$var wire 1 3 B $end
$var wire 1 4 X $end
$upscope $end
$scope module b0 $end
$var wire 1 2 A $end
$var wire 1 3 B $end
$var wire 1 5 X $end
$upscope $end
$upscope $end
$scope module bbb $end
$var wire 1 6 c $end
$var wire 1 7 count0 $end
$var wire 1 8 count1 $end
$var wire 1 9 count2 $end
$var wire 1 : count3 $end
$var wire 4 ; d [3:0] $end
$var wire 4 < t [3:0] $end
$var wire 4 = x [3:0] $end
$scope module b3 $end
$var wire 1 > A $end
$var wire 1 6 B $end
$var wire 1 ? X $end
$upscope $end
$scope module b2 $end
$var wire 1 @ A $end
$var wire 1 6 B $end
$var wire 1 A X $end
$upscope $end
$scope module b1 $end
$var wire 1 B A $end
$var wire 1 6 B $end
$var wire 1 C X $end
$upscope $end
$scope module b0 $end
$var wire 1 D A $end
$var wire 1 6 B $end
$var wire 1 E X $end
$upscope $end
$scope module bb0 $end
$var wire 1 F a $end
$var wire 1 G b $end
$var wire 1 H c1 $end
$var wire 1 I c2 $end
$var wire 1 J cin $end
$var wire 1 7 cout $end
$var wire 1 K s $end
$var wire 1 L s1 $end
$scope module half1 $end
$var wire 1 L X $end
$var wire 1 H Y $end
$var wire 1 F a $end
$var wire 1 G b $end
$scope module aaa $end
$var wire 1 F A $end
$var wire 1 G B $end
$var wire 1 L X $end
$upscope $end
$scope module bbb $end
$var wire 1 F A $end
$var wire 1 G B $end
$var wire 1 H X $end
$upscope $end
$upscope $end
$scope module half2 $end
$var wire 1 K X $end
$var wire 1 I Y $end
$var wire 1 J a $end
$var wire 1 L b $end
$scope module aaa $end
$var wire 1 J A $end
$var wire 1 L B $end
$var wire 1 K X $end
$upscope $end
$scope module bbb $end
$var wire 1 J A $end
$var wire 1 L B $end
$var wire 1 I X $end
$upscope $end
$upscope $end
$scope module b3 $end
$var wire 1 H A $end
$var wire 1 I B $end
$var wire 1 7 X $end
$upscope $end
$upscope $end
$scope module bb1 $end
$var wire 1 M a $end
$var wire 1 N b $end
$var wire 1 O c1 $end
$var wire 1 P c2 $end
$var wire 1 7 cin $end
$var wire 1 8 cout $end
$var wire 1 Q s $end
$var wire 1 R s1 $end
$scope module half1 $end
$var wire 1 R X $end
$var wire 1 O Y $end
$var wire 1 M a $end
$var wire 1 N b $end
$scope module aaa $end
$var wire 1 M A $end
$var wire 1 N B $end
$var wire 1 R X $end
$upscope $end
$scope module bbb $end
$var wire 1 M A $end
$var wire 1 N B $end
$var wire 1 O X $end
$upscope $end
$upscope $end
$scope module half2 $end
$var wire 1 Q X $end
$var wire 1 P Y $end
$var wire 1 7 a $end
$var wire 1 R b $end
$scope module aaa $end
$var wire 1 7 A $end
$var wire 1 R B $end
$var wire 1 Q X $end
$upscope $end
$scope module bbb $end
$var wire 1 7 A $end
$var wire 1 R B $end
$var wire 1 P X $end
$upscope $end
$upscope $end
$scope module b3 $end
$var wire 1 O A $end
$var wire 1 P B $end
$var wire 1 8 X $end
$upscope $end
$upscope $end
$scope module bb2 $end
$var wire 1 S a $end
$var wire 1 T b $end
$var wire 1 U c1 $end
$var wire 1 V c2 $end
$var wire 1 8 cin $end
$var wire 1 9 cout $end
$var wire 1 W s $end
$var wire 1 X s1 $end
$scope module half1 $end
$var wire 1 X X $end
$var wire 1 U Y $end
$var wire 1 S a $end
$var wire 1 T b $end
$scope module aaa $end
$var wire 1 S A $end
$var wire 1 T B $end
$var wire 1 X X $end
$upscope $end
$scope module bbb $end
$var wire 1 S A $end
$var wire 1 T B $end
$var wire 1 U X $end
$upscope $end
$upscope $end
$scope module half2 $end
$var wire 1 W X $end
$var wire 1 V Y $end
$var wire 1 8 a $end
$var wire 1 X b $end
$scope module aaa $end
$var wire 1 8 A $end
$var wire 1 X B $end
$var wire 1 W X $end
$upscope $end
$scope module bbb $end
$var wire 1 8 A $end
$var wire 1 X B $end
$var wire 1 V X $end
$upscope $end
$upscope $end
$scope module b3 $end
$var wire 1 U A $end
$var wire 1 V B $end
$var wire 1 9 X $end
$upscope $end
$upscope $end
$scope module bb3 $end
$var wire 1 Y a $end
$var wire 1 Z b $end
$var wire 1 [ c1 $end
$var wire 1 \ c2 $end
$var wire 1 9 cin $end
$var wire 1 : cout $end
$var wire 1 ] s $end
$var wire 1 ^ s1 $end
$scope module half1 $end
$var wire 1 ^ X $end
$var wire 1 [ Y $end
$var wire 1 Y a $end
$var wire 1 Z b $end
$scope module aaa $end
$var wire 1 Y A $end
$var wire 1 Z B $end
$var wire 1 ^ X $end
$upscope $end
$scope module bbb $end
$var wire 1 Y A $end
$var wire 1 Z B $end
$var wire 1 [ X $end
$upscope $end
$upscope $end
$scope module half2 $end
$var wire 1 ] X $end
$var wire 1 \ Y $end
$var wire 1 9 a $end
$var wire 1 ^ b $end
$scope module aaa $end
$var wire 1 9 A $end
$var wire 1 ^ B $end
$var wire 1 ] X $end
$upscope $end
$scope module bbb $end
$var wire 1 9 A $end
$var wire 1 ^ B $end
$var wire 1 \ X $end
$upscope $end
$upscope $end
$scope module b3 $end
$var wire 1 [ A $end
$var wire 1 \ B $end
$var wire 1 : X $end
$upscope $end
$upscope $end
$upscope $end
$upscope $end
$upscope $end
$enddefinitions $end
#0
$dumpvars
1^
0]
1\
0[
1Z
0Y
1X
0W
1V
0U
1T
0S
1R
0Q
1P
0O
1N
0M
1L
0K
1J
1I
0H
1G
0F
1E
0D
1C
0B
1A
0@
1?
0>
b1111 =
b0 <
b0 ;
1:
19
18
17
16
05
04
03
02
01
00
0/
0.
0-
0,
b0 +
b0 *
b0 )
b0 (
b0 '
b0 &
b0 %
b0 $
b0 #
b0 "
b0 !
$end
#10
b1 '
b0 "
b0 #
#20
1,
11
b1 &
b0 '
b1 "
b1 (
b0 #
#30
1-
12
0,
01
b1 '
b10 "
b10 (
b0 #
#40
1,
11
b1 %
b0 &
b0 '
b11 "
b11 (
b0 #
#50
0-
02
0,
01
13
b1 '
b0 "
b0 (
b1 #
b1 )
#60
0:
1]
0\
09
1W
0V
08
1Q
0P
07
1K
b1111 !
b1111 *
b1111 ;
0I
0L
0G
0E
b1110 =
1D
14
b1 +
b1 <
1,
11
b1 &
b0 '
b1 "
b1 (
b1 #
#70
17
1Q
0K
b1110 !
b1110 *
b1110 ;
1I
0R
1L
0N
1G
0C
1E
b1101 =
1B
0D
15
04
b10 +
b10 <
1-
12
0,
01
b1 '
b10 "
b10 (
b1 #
#80
0Q
07
1K
b1101 !
b1101 *
b1101 ;
0I
0L
0G
0E
b1100 =
1D
14
b11 +
b11 <
1,
11
b1 $
b0 %
b0 &
b0 '
b11 "
b11 (
b1 #
#90
1:
0]
1\
19
0W
1V
18
1P
17
0K
1I
0Q
b0 !
b0 *
b0 ;
1L
1R
1G
1N
1E
1C
b1111 =
0D
0B
04
05
b0 +
b0 <
0-
02
0,
01
1.
03
b1 '
b0 "
b0 (
b10 #
b10 )
#100
1W
b100 !
b100 *
b100 ;
0V
0X
1U
1S
1/
b100 +
b100 <
1,
11
b1 &
b0 '
b1 "
b1 (
b10 #
#110
1:
0]
1\
1Q
0P
0W
b10 !
b10 *
b10 ;
1V
19
0R
1O
1X
0U
1M
0S
10
0/
b1000 +
b1000 <
1-
12
0,
01
b1 '
b10 "
b10 (
b10 #
#120
1W
b110 !
b110 *
b110 ;
0V
0X
1U
1S
1/
b1100 +
b1100 <
1,
11
b1 %
b0 &
b0 '
b11 "
b11 (
b10 #
#130
1:
0]
1\
0Q
1P
18
0W
b0 !
b0 *
b0 ;
1V
19
1R
0O
1X
0U
0M
0S
00
0/
b0 +
b0 <
0-
02
0,
01
13
b1 '
b0 "
b0 (
b11 #
b11 )
#140
08
1Q
0P
07
1K
0I
0L
0W
b11 !
b11 *
b11 ;
0V
0G
0X
1U
0E
b1110 =
1S
1D
1/
14
b101 +
b101 <
1,
11
b1 &
b0 '
b1 "
b1 (
b11 #
#150
1P
17
1:
0K
1I
1V
0]
1\
1L
0Q
18
0N
0W
b0 !
b0 *
b0 ;
19
1G
1R
0O
0C
1X
0U
1E
b1101 =
1M
1B
0S
0D
10
15
0/
04
b1010 +
b1010 <
1-
12
0,
01
b1 '
b10 "
b10 (
b11 #
#160
08
1Q
0P
07
1K
0I
0L
0W
b11 !
b11 *
b11 ;
0V
0G
0X
1U
0E
b1100 =
1S
1D
1/
14
b1111 +
b1111 <
1,
11
b10 $
b10 %
b10 &
b10 '
b11 "
b11 (
b11 #
